{
  "parent": "minecraft:recipes/root",
  "rewards": {
    "recipes": [
      "crypticcosmos:polished_lunon_slab_from_polished_lunon_stonecutting"
    ]
  },
  "criteria": {
    "has_polished_lunon": {
      "trigger": "minecraft:inventory_changed",
      "conditions": {
        "items": [
          {
            "item": "crypticcosmos:polished_lunon"
          }
        ]
      }
    },
    "has_the_recipe": {
      "trigger": "minecraft:recipe_unlocked",
      "conditions": {
        "recipe": "crypticcosmos:polished_lunon_slab_from_polished_lunon_stonecutting"
      }
    }
  },
  "requirements": [
    [
      "has_polished_lunon",
      "has_the_recipe"
    ]
  ]
}